invenhost_core/InvenHostCore.py
invenhost_core/__init__.py
invenhost_core-0.3.0.dist-info/METADATA
invenhost_core-0.3.0.dist-info/WHEEL
invenhost_core-0.3.0.dist-info/entry_points.txt
invenhost_core-0.3.0.dist-info/top_level.txt
invenhost_core-0.3.0.dist-info/RECORD
