Metadata-Version: 2.1
Name: invenhost-core
Version: 0.3.0
Summary: InvenHost integration plugin
Author-email: Matthias Mair <code@mjmair.com>
License: UNLICENSED
Project-URL: Repository, https://github.com/invenhost/invenhost-core
Project-URL: Bug Tracker, https://github.com/invenhost/invenhost-core/issues
Keywords: inventree,inventree-plugin,invenhost-core
Classifier: Programming Language :: Python :: 3
Classifier: Operating System :: OS Independent
Classifier: Development Status :: 5 - Production/Stable
Classifier: Environment :: Plugins
Classifier: Framework :: Django
Classifier: Intended Audience :: Developers
Classifier: Intended Audience :: Manufacturing
Classifier: Intended Audience :: End Users/Desktop
Classifier: Topic :: Scientific/Engineering
Requires-Python: >=3.9
Requires-Dist: django
Provides-Extra: dev
Requires-Dist: twine ; extra == 'dev'
Requires-Dist: setuptools ; extra == 'dev'
